multi_swe_bench/__init__.py
multi_swe_bench/collect/__init__.py
multi_swe_bench/collect/build_dataset.py
multi_swe_bench/collect/crawl_repos.py
multi_swe_bench/collect/filter_prs.py
multi_swe_bench/collect/get_all_prs.py
multi_swe_bench/collect/get_from_repos_pipeline.py
multi_swe_bench/collect/get_pipeline.py
multi_swe_bench/collect/get_related_issues.py
multi_swe_bench/collect/merge_prs_with_issues.py
multi_swe_bench/collect/util.py
multi_swe_bench/harness/__init__.py
multi_swe_bench/harness/build_dataset.py
multi_swe_bench/harness/constant.py
multi_swe_bench/harness/dataset.py
multi_swe_bench/harness/gen_report.py
multi_swe_bench/harness/image.py
multi_swe_bench/harness/instance.py
multi_swe_bench/harness/pull_request.py
multi_swe_bench/harness/report.py
multi_swe_bench/harness/run_evaluation.py
multi_swe_bench/harness/test_result.py
multi_swe_bench/harness/repos/__init__.py
multi_swe_bench/harness/repos/c/__init__.py
multi_swe_bench/harness/repos/c/OpenMathLib/OpenBLAS.py
multi_swe_bench/harness/repos/c/OpenMathLib/__init__.py
multi_swe_bench/harness/repos/c/facebook/__init__.py
multi_swe_bench/harness/repos/c/facebook/zstd.py
multi_swe_bench/harness/repos/c/fluent/__init__.py
multi_swe_bench/harness/repos/c/fluent/fluentbit.py
multi_swe_bench/harness/repos/c/jqlang/__init__.py
multi_swe_bench/harness/repos/c/jqlang/jq.py
multi_swe_bench/harness/repos/c/libgit2/__init__.py
multi_swe_bench/harness/repos/c/libgit2/libgit2.py
multi_swe_bench/harness/repos/c/libsdlorg/SDL.py
multi_swe_bench/harness/repos/c/libsdlorg/__init__.py
multi_swe_bench/harness/repos/c/mruby/__init__.py
multi_swe_bench/harness/repos/c/mruby/mruby.py
multi_swe_bench/harness/repos/c/php/__init__.py
multi_swe_bench/harness/repos/c/php/phpsrc.py
multi_swe_bench/harness/repos/c/ponylang/__init__.py
multi_swe_bench/harness/repos/c/ponylang/ponyc.py
multi_swe_bench/harness/repos/c/redis/__init__.py
multi_swe_bench/harness/repos/c/redis/redis.py
multi_swe_bench/harness/repos/c/valkey_io/__init__.py
multi_swe_bench-0.1.2.dist-info/licenses/LICENSE
multi_swe_bench-0.1.2.dist-info/METADATA
multi_swe_bench-0.1.2.dist-info/WHEEL
multi_swe_bench-0.1.2.dist-info/top_level.txt
multi_swe_bench-0.1.2.dist-info/RECORD
