Metadata-Version: 2.4
Name: multi-swe-bench
Version: 0.1.2
Summary: Multi-SWE-bench: A Multilingual Benchmark for Issue Resolving
Home-page: https://github.com/multi-swe-bench/multi-swe-bench
Author: Daoguang Zan
Author-email: zandaoguang@bytedance.com
Classifier: Programming Language :: Python :: 3
Classifier: License :: OSI Approved :: Apache Software License
Classifier: Operating System :: OS Independent
Requires-Python: >=3.10
License-File: LICENSE
Requires-Dist: dataclasses_json
Requires-Dist: docker
Requires-Dist: tqdm
Requires-Dist: gitpython
Requires-Dist: toml
Requires-Dist: pyyaml
Requires-Dist: PyGithub
Requires-Dist: unidiff
Dynamic: author
Dynamic: author-email
Dynamic: classifier
Dynamic: description
Dynamic: description-content-type
Dynamic: home-page
Dynamic: license-file
Dynamic: requires-dist
Dynamic: requires-python
Dynamic: summary
